JupyterLibrary/__init__.py
JupyterLibrary/_version.py
JupyterLibrary/constants.py
JupyterLibrary/core.py
JupyterLibrary/magic.py
JupyterLibrary/clients/README.md
JupyterLibrary/clients/classic/Commands.resource
JupyterLibrary/clients/classic/Notebook.resource
JupyterLibrary/clients/classic/Output.resource
JupyterLibrary/clients/classic/Selectors.resource
JupyterLibrary/clients/classic/Tree.resource
JupyterLibrary/clients/jupyterlab/Commands.resource
JupyterLibrary/clients/jupyterlab/Icons.resource
JupyterLibrary/clients/jupyterlab/Launcher.resource
JupyterLibrary/clients/jupyterlab/Notebook.resource
JupyterLibrary/clients/jupyterlab/Output.resource
JupyterLibrary/clients/jupyterlab/PageInfo.resource
JupyterLibrary/clients/jupyterlab/Selectors.resource
JupyterLibrary/clients/jupyterlab/Settings.resource
JupyterLibrary/clients/jupyterlab/Shell.resource
JupyterLibrary/clients/jupyterlab/Shortcuts.resource
JupyterLibrary/clients/jupyterlab/Sidebar.resource
JupyterLibrary/clients/jupyterlab/Version.resource
JupyterLibrary/clients/notebook/Commands.resource
JupyterLibrary/clients/notebook/Notebook.resource
JupyterLibrary/clients/notebook/Output.resource
JupyterLibrary/clients/notebook/Selectors.resource
JupyterLibrary/clients/notebook/Tree.resource
JupyterLibrary/common/CodeMirror.resource
JupyterLibrary/common/Lumino.resource
JupyterLibrary/keywords/__init__.py
JupyterLibrary/keywords/server.py
JupyterLibrary/keywords/webelements.py
robotframework_jupyterlibrary-0.5.0.dist-info/LICENSE
robotframework_jupyterlibrary-0.5.0.dist-info/WHEEL
robotframework_jupyterlibrary-0.5.0.dist-info/METADATA
robotframework_jupyterlibrary-0.5.0.dist-info/RECORD
