Metadata-Version: 2.1
Name: robotframework-jupyterlibrary
Version: 0.5.0
Summary: A Robot Framework library for automating (testing of) Jupyter end-user applications and extensions.
Keywords: Interactive,Jupyter,notebook,Testing,Web
Author-email: JupyterLibrary contributors <robots-from-jupyter@googlegroups.com>
Requires-Python: >=3.8
Classifier: Framework :: Jupyter
Classifier: Framework :: Jupyter :: JupyterLab
Classifier: Framework :: Jupyter :: JupyterLab :: 3
Classifier: Framework :: Jupyter :: JupyterLab :: 4
Classifier: Intended Audience :: Developers
Classifier: Intended Audience :: Information Technology
Classifier: License :: OSI Approved :: BSD License
Classifier: Programming Language :: Python
Classifier: Programming Language :: Python :: 3.8
Classifier: Programming Language :: Python :: 3.9
Classifier: Programming Language :: Python :: 3.10
Classifier: Programming Language :: Python :: 3.11
Classifier: Programming Language :: Python :: 3 :: Only
Classifier: Topic :: Software Development :: Quality Assurance
Classifier: Topic :: Software Development :: Testing
Requires-Dist: robotframework >=5
Requires-Dist: robotframework-seleniumlibrary >=5
Requires-Dist: robotframwork-tidy ; extra == "tidy"
Requires-Dist: ipywidgets ; extra == "widgets"
Project-URL: Bug Tracker, https://github.com/robots-from-jupyter/robotframework-jupyterlibrary/issues
Project-URL: CI, https://github.com/robots-from-jupyter/robotframework-jupyterlibrary/actions
Project-URL: Changelog, https://github.com/robots-from-jupyter/robotframework-jupyterlibrary/blob/main/docs/HISTORY.ipynb
Project-URL: Documentation, https://robotframework-jupyterlibrary.readthedocs.io/en/stable
Project-URL: Releases, https://github.com/robots-from-jupyter/robotframework-jupyterlibrary/releases
Project-URL: Source Code, https://github.com/robots-from-jupyter/robotframework-jupyterlibrary
Provides-Extra: tidy
Provides-Extra: widgets
